net_speed_checker/__init__.py
net_speed_checker/check_speed.py
test/__init__.py
test/test_import.py
net_speed_checker-0.3.dist-info/LICENSE
net_speed_checker-0.3.dist-info/METADATA
net_speed_checker-0.3.dist-info/WHEEL
net_speed_checker-0.3.dist-info/top_level.txt
net_speed_checker-0.3.dist-info/RECORD
