Metadata-Version: 2.1
Name: net-speed-checker
Version: 0.3
Summary: Package taking measurements for internet speed.
Home-page: https://github.com/radupetre/net-speed-checker
Author: Radu Petre
Author-email: Spam@Petre.dev
License: MIT License
Download-URL: https://github.com/radupetre/net-speed-checker/archive/v0.2.tar.gz
Keywords: SPEEDTEST,SPEEDCHECKER,SPEED,TEST,CHECKER
Platform: UNKNOWN
Classifier: Development Status :: 4 - Beta
Classifier: Programming Language :: Python :: 3
Classifier: License :: OSI Approved :: MIT License
Classifier: Operating System :: OS Independent
Requires-Python: >=3.6
Requires-Dist: speedtest-cli
Requires-Dist: mysql-connector-python
Requires-Dist: SQLAlchemy
Requires-Dist: mysqlclient
